microscPSF/__init__.py
microscPSF/microscPSF.py
microscPSF/test/test.py
microscPSF/test/test_fscan.py
MicroscPSF_Py-0.2.dist-info/LICENSE.txt
MicroscPSF_Py-0.2.dist-info/METADATA
MicroscPSF_Py-0.2.dist-info/WHEEL
MicroscPSF_Py-0.2.dist-info/top_level.txt
MicroscPSF_Py-0.2.dist-info/RECORD
