Metadata-Version: 2.1
Name: MicroscPSF-Py
Version: 0.2
Summary: Gibson-Lanni PSF calculation code.
Home-page: https://github.com/MicroscPSF/MicroscPSF-Py
Author: Kyle Douglass, Hazen Babcock
Author-email: hbabcock@mac.com
License: MIT
Keywords: PSF,microscopy
Platform: UNKNOWN
Classifier: Development Status :: 3 - Alpha
Classifier: Intended Audience :: Developers
Classifier: License :: OSI Approved :: MIT License
Classifier: Programming Language :: C
Classifier: Programming Language :: Python :: 2
Classifier: Programming Language :: Python :: 2.7
Classifier: Programming Language :: Python :: 3
Classifier: Programming Language :: Python :: 3.5
Classifier: Programming Language :: Python :: 3.6
